airflow_arcgis/__init__.py
airflow_arcgis/arcgis_plugin.py
airflow_arcgis/hooks/__init__.py
airflow_arcgis/hooks/arcgis_hook.py
airflow_arcgis/operators/__init__.py
airflow_arcgis/operators/arcgis_operator.py
airflow_arcgis_plugin-0.0.1.dist-info/LICENSE
airflow_arcgis_plugin-0.0.1.dist-info/METADATA
airflow_arcgis_plugin-0.0.1.dist-info/WHEEL
airflow_arcgis_plugin-0.0.1.dist-info/entry_points.txt
airflow_arcgis_plugin-0.0.1.dist-info/top_level.txt
airflow_arcgis_plugin-0.0.1.dist-info/RECORD
